axe_hash.cpython-34m.so
axe_hash-1.3.7.dist-info/metadata.json
axe_hash-1.3.7.dist-info/WHEEL
axe_hash-1.3.7.dist-info/top_level.txt
axe_hash-1.3.7.dist-info/DESCRIPTION.rst
axe_hash-1.3.7.dist-info/METADATA
axe_hash-1.3.7.dist-info/RECORD
