Metadata-Version: 2.0
Name: axe-hash
Version: 1.3.7
Summary: Binding for AXE X11 proof of work hashing.
Home-page: https://github.com/axerunners/axe_hash
Author: UNKNOWN
Author-email: UNKNOWN
License: MIT
Platform: UNKNOWN
